{
  "name": "activemq",
  "trademark": "ActiveMQ",
  "release": true,
  "fork_url": "https://github.com/apache/activemq-artemis/tree/main/artemis-docker",
  "docker_url": "https://hub.docker.com/r/alfresco/alfresco-activemq/tags",
  "edition": [
    {
      "dist": "community",
      "version": [
        "5.18.2-jre17-rockylinux8"
      ]
    },
    {
      "dist": "classic",
      "version": [
        "5.18.2-jre17-rockylinux8"
      ]
    },
    {
      "dist": "artemis",
      "version": [
        "2.21.0"
      ]
    }
  ],
  "requirements": {
    "cpu": "1",
    "memory": "1",
    "disk": "2",
    "url": "https://github.com/apache/activemq-artemis"
  }
}
